nadypy/__init__.py
nadypy/api/__init__.py
nadypy/api/config/__init__.py
nadypy/api/config/get_access_levels.py
nadypy/api/config/get_module.py
nadypy/api/config/get_module_module_commands.py
nadypy/api/config/get_module_module_description.py
nadypy/api/config/get_module_module_events.py
nadypy/api/config/get_module_module_settings.py
nadypy/api/config/patch_module_module.py
nadypy/api/config/patch_module_module_commands_command.py
nadypy/api/config/patch_module_module_commands_command_channel.py
nadypy/api/config/patch_module_module_events_event_handler.py
nadypy/api/config/patch_module_module_settings_setting.py
nadypy/api/config/put_module_module.py
nadypy/api/config/put_module_module_commands_command.py
nadypy/api/config/put_module_module_commands_command_channel.py
nadypy/api/config/put_module_module_events_event_handler.py
nadypy/api/config/put_module_module_settings_setting.py
nadypy/api/guild/__init__.py
nadypy/api/guild/get_org_history.py
nadypy/api/messages/__init__.py
nadypy/api/messages/get_hop_color.py
nadypy/api/messages/get_hop_format.py
nadypy/api/news/__init__.py
nadypy/api/news/get_news.py
nadypy/api/news/get_news_id.py
nadypy/api/news/patch_news_id.py
nadypy/api/news/post_news.py
nadypy/api/online/__init__.py
nadypy/api/online/get_online.py
nadypy/api/preferences/__init__.py
nadypy/api/preferences/delete_setting_key.py
nadypy/api/preferences/get_setting_key.py
nadypy/api/preferences/post_setting_key.py
nadypy/api/preferences/put_setting_key.py
nadypy/api/profile/__init__.py
nadypy/api/profile/delete_profile_profile.py
nadypy/api/profile/get_profile.py
nadypy/api/profile/get_profile_profile.py
nadypy/api/profile/patch_profile_profile.py
nadypy/api/profile/post_profile_profile.py
nadypy/api/profile/put_profile_profile.py
nadypy/api/relay/__init__.py
nadypy/api/relay/delete_relay_relay.py
nadypy/api/relay/get_relay.py
nadypy/api/relay/get_relay_component_layer.py
nadypy/api/relay/get_relay_component_protocol.py
nadypy-5.2.2.dist-info/LICENSE
nadypy-5.2.2.dist-info/WHEEL
nadypy-5.2.2.dist-info/METADATA
nadypy-5.2.2.dist-info/RECORD
