Metadata-Version: 2.1
Name: nadypy
Version: 5.2.2
Summary: A client library for accessing a Nadybot's API
Home-page: https://github.com/Nadybot/nadypy
License: MIT
Author: Jens Reidel
Author-email: adrian@travitia.xyz
Requires-Python: >=3.6,<4.0
Classifier: License :: OSI Approved :: MIT License
Classifier: Programming Language :: Python :: 3
Classifier: Programming Language :: Python :: 3.6
Classifier: Programming Language :: Python :: 3.7
Classifier: Programming Language :: Python :: 3.8
Requires-Dist: attrs (>=20.1.0,<22.0.0)
Requires-Dist: httpx (>=0.15.4,<0.21.0)
Requires-Dist: pyopenssl (>=20.0.1,<21.0.0)
Requires-Dist: python-dateutil (>=2.8.0,<3.0.0)
Project-URL: Repository, https://github.com/Nadybot/nadypy
